nsekit_mcp/__init__.py
nsekit_mcp/server.py
nsekit_mcp-0.0.19.dist-info/METADATA
nsekit_mcp-0.0.19.dist-info/WHEEL
nsekit_mcp-0.0.19.dist-info/entry_points.txt
nsekit_mcp-0.0.19.dist-info/RECORD
