Metadata-Version: 2.4
Name: nsekit-mcp
Version: 0.0.19
Summary: FastMCP server for NSE India market data using NseKit
Requires-Python: >=3.12
Requires-Dist: mcp[cli]>=1.22.0
Requires-Dist: nsekit>=0.0.19
Requires-Dist: typer>=0.20.0
